bg_helper_utils/__init__.py
bg_helper_utils/console_helper.py
bg_helper_utils/file_utils.py
bg_helper_utils/find_batch_analysis_dir.py
bg_helper_utils/find_samplesheet.py
bg_helper_utils/helper.py
bg_helper_utils/make_shell_scripts_and_aliases.py
bg_helper_utils/progress_bar.py
bg_helper_utils/conf/config.yaml
bg_helper_utils-0.6.0.dist-info/AUTHORS.rst
bg_helper_utils-0.6.0.dist-info/LICENSE
bg_helper_utils-0.6.0.dist-info/METADATA
bg_helper_utils-0.6.0.dist-info/WHEEL
bg_helper_utils-0.6.0.dist-info/entry_points.txt
bg_helper_utils-0.6.0.dist-info/top_level.txt
bg_helper_utils-0.6.0.dist-info/RECORD
