Metadata-Version: 2.1
Name: bg_helper_utils
Version: 0.6.0
Summary: Collection of Python convenience scripts for BG tasks.
Home-page: https://github.com/jai-python3/bg-helper-utils
Author: Jaideep Sundaram
Author-email: jai.python3@gmail.com
Keywords: bg_helper_utils
Classifier: Development Status :: 2 - Pre-Alpha
Classifier: Intended Audience :: Developers
Classifier: Natural Language :: English
Classifier: Programming Language :: Python :: 3
Classifier: Programming Language :: Python :: 3.6
Classifier: Programming Language :: Python :: 3.7
Classifier: Programming Language :: Python :: 3.8
Requires-Python: >=3.6
License-File: LICENSE
License-File: AUTHORS.rst
Requires-Dist: Click >=7.0
Requires-Dist: Rich
Requires-Dist: PyYAML
